hm_semester/__init__.py
hm_semester/__main__.py
hm_semester/agenda.py
hm_semester/const.py
hm_semester/semester.py
hm_semester/types.py
hm_semester/util.py
hm_semester-26.1.0.dist-info/METADATA
hm_semester-26.1.0.dist-info/WHEEL
hm_semester-26.1.0.dist-info/top_level.txt
hm_semester-26.1.0.dist-info/RECORD
