Metadata-Version: 2.4
Name: hm-semester
Version: 26.1.0
Summary: A Python package for semester-related utilities.
Author: David M. Straub
License: MIT
Project-URL: Homepage, https://github.com/DavidMStraub/hm-semester
Classifier: Programming Language :: Python :: 3.10
Classifier: License :: OSI Approved :: MIT License
Classifier: Operating System :: OS Independent
Requires-Python: >=3.10
Requires-Dist: icalendar>=5.0.0
Requires-Dist: click>=8.0.0
